{"description": "$5 / Age 18 And Up\n\nAdditional Info:\nCNY's Premier Phish Cover Band. $5\nTickets:\nhttp://www.ticketweb.com/event/phish-night-w-dinner-and-funk-n-waffles-music-hall-tickets/7873415?REFERRAL_ID=twfb", "start_time": "2018-01-02T20:00:00-0500", "priority": "9", "place": {"id": "86659589746", "name": "Funk 'n Waffles Rochester", "location": {"city": "Rochester", "zip": "14604", "country": "United States", "longitude": -77.61141, "state": "NY", "street": "204 N Water St", "latitude": 43.16048}}, "id": "136612453775420", "name": "Phish Night w/ Dinner and a Movie"}